bhumi-0.4.82.dist-info/METADATA
bhumi-0.4.82.dist-info/WHEEL
bhumi-0.4.82.dist-info/licenses/LICENSE
bhumi.libs/libcom_err-2abe824b.so.2
bhumi.libs/libcrypto-d3570994.so.10
bhumi.libs/libgssapi_krb5-497db0c6.so.2
bhumi.libs/libk5crypto-b1f99d5c.so.3
bhumi.libs/libkeyutils-dfe70bd6.so.1
bhumi.libs/libkrb5-fcafa220.so.3
bhumi.libs/libkrb5support-d0bcff84.so.0
bhumi.libs/libpcre-9513aab5.so.1
bhumi.libs/libselinux-0922c95c.so.1
bhumi.libs/libssl-cd1d6220.so.10
bhumi/__init__.py
bhumi/base.py
bhumi/base_client.py
bhumi/bhumi.cpython-38-x86_64-linux-gnu.so
bhumi/client.py
bhumi/core.py
bhumi/data/__init__.py
bhumi/data/archive_latest.json
bhumi/json_compat.py
bhumi/map_elites_buffer.py
bhumi/models/__init__.py
bhumi/models/gemini.py
bhumi/models/openai.py
bhumi/providers/__init__.py
bhumi/providers/anthropic_client.py
bhumi/providers/gemini_client.py
bhumi/providers/groq_client.py
bhumi/providers/openai_client.py
bhumi/providers/openai_provider.py
bhumi/providers/sambanova_client.py
bhumi/structured_outputs.py
bhumi/tools.py
bhumi/utils.py
bhumi-0.4.82.dist-info/RECORD
