Metadata-Version: 2.4
Name: bhumi
Version: 0.4.82
Classifier: Programming Language :: Rust
Classifier: Programming Language :: Python :: Implementation :: CPython
Requires-Dist: satya>=0.3.7 ; python_full_version >= '3.10'
Requires-Dist: satya>=0.2.6 ; python_full_version < '3.10'
License-File: LICENSE
Summary: High performance LLM client
Home-Page: https://github.com/justrach/bhumi
Author-email: Rach Pradhan <rach@rachpradhan.com>
Requires-Python: >=3.8
